[{
	"Country": "Venezuela",
	"Area": "Humanidades", 
	"Job": "Abogado",
	"Vacant": 3,
	"Description": "Para importante estudio jurídico con fuerte orientación a parte demandada requerimos profesional graduado con matricula en CABA que cuente con al menos 3 años de experiencia llevando adelante litigios en área civil y comercial desempeñadas en estudio o en empresas. Contratación en relación de dependencia Formal. Completan el perfil excelentes habilidades de negociación, comunicación y relaciones interpersonales, deseable conocimiento de idioma ingles. Aguardamos tu Postulacion. Muchas Gracias ¡! Equipo Hucap"
},

{
    "Country": "Argentina",
	"Area": "Ingenieria", 
	"Job": "Developer web",
	"Vacant": 3,
	"Description":"Importante proyecto"
},
{
    "Country": "Colombia",
	"Area": "Ingenieria", 
	"Job": "Maquetador",
	"Vacant": 3,
	"Description":"Importante proyecto"
},
{
    "Country": "Argentina",
	"Area": "Contabilidad", 
	"Job": "Contador",
	"Vacant": 3,
	"Description":"Importante negocio"
}
]